design.v
module vending_machine(
    input clk,reset,coin5,coin10,
    output reg dispense
);
reg[1:0]state;
parameter s0 = 2'b00;
parameter s5 = 2'b01;
parameter s10 = 2'b10;
parameter s15 = 2'b11;
always @(posedge clk or posedge reset)
begin
    if(reset)
    begin
        state <= s0;
        dispense <= 0;
    end
    else
    begin
        dispense <= 0;
        case(state)
            s0:
            begin
                if(coin5)
                    state <= s5;
                else if(coin10)
                     state <= s10;
            end
            s5:
            begin
                if(coin5)
                    state <= s10;
                else if(coin10)
                     state <= s15;
            end
            s10:
            begin
                if(coin5||coin10)
                    state <= s15;
            end
            s15:
            begin
                dispense <= 1;
                state <= s0;
            end
        endcase
    end
end
endmodule

testbench.v
`timescale 1ps/1ps
module test;
reg clk;
reg reset;
reg coin5;
reg coin10;
wire dispense;
vending_machine uut(
    .clk(clk),.reset(reset),.coin5(coin5),.coin10(coin10),.dispense(dispense)
);
always #5 clk = ~clk;
initial begin
    $dumpfile("dump.vcd");
    $dumpvars(0,test);
    clk = 0;
    reset = 1;
    coin5 = 0;
    coin10 = 0;
    #10 reset = 0;

    #10 coin5 = 1;
    #10 coin5 = 0;

    #10 coin10 = 1;
    #10 coin10 = 1;

    #30 coin10 = 1;
    #10 coin10 = 0;

    #10 coin5 = 1;
    #10 coin5 = 0;

    #50 $finish;
end
endmodule

dump.vcd
$date
	Tue Jun 16 11:19:17 2026
$end
$version
	Icarus Verilog
$end
$timescale
	1ps
$end
$scope module test $end
$var wire 1 ! dispense $end
$var reg 1 " clk $end
$var reg 1 # coin10 $end
$var reg 1 $ coin5 $end
$var reg 1 % reset $end
$scope module uut $end
$var wire 1 " clk $end
$var wire 1 # coin10 $end
$var wire 1 $ coin5 $end
$var wire 1 % reset $end
$var parameter 2 & s0 $end
$var parameter 2 ' s10 $end
$var parameter 2 ( s15 $end
$var parameter 2 ) s5 $end
$var reg 1 ! dispense $end
$var reg 2 * state [1:0] $end
$upscope $end
$upscope $end
$enddefinitions $end
$comment Show the parameter values. $end
$dumpall
b1 )
b11 (
b10 '
b0 &
$end
#0
$dumpvars
b0 *
1%
0$
0#
0"
0!
$end
#5
1"
#10
0"
0%
#15
1"
#20
0"
1$
#25
b1 *
1"
#30
0"
0$
#35
1"
#40
0"
1#
#45
b11 *
1"
#50
0"
#55
b0 *
1!
1"
#60
0"
#65
b10 *
0!
1"
#70
0"
#75
b11 *
1"
#80
0"
#85
b0 *
1!
1"
#90
0"
0#
#95
0!
1"
#100
0"
1$
#105
b1 *
1"
#110
0"
0$
